pygrowwapi/__init__.py
pygrowwapi/client.py
pygrowwapi/model.py
pygrowwapi-0.3.1.dist-info/METADATA
pygrowwapi-0.3.1.dist-info/WHEEL
pygrowwapi-0.3.1.dist-info/licenses/LICENSE
pygrowwapi-0.3.1.dist-info/RECORD
